LICENSE.md
README.md
setup.py
mindpark/__init__.py
mindpark/__main__.py
mindpark.egg-info/PKG-INFO
mindpark.egg-info/SOURCES.txt
mindpark.egg-info/dependency_links.txt
mindpark.egg-info/top_level.txt
test/test_algorithm.py
test/test_run.py
test/test_step.py