Metadata-Version: 2.1
Name: mindpark
Version: 1.0.0
Summary: Testbed for deep reinforcement learning
Home-page: http://github.com/danijar/mindpark
Classifier: Intended Audience :: Science/Research
Classifier: License :: OSI Approved :: MIT License
Classifier: Programming Language :: Python :: 3
License-File: LICENSE.md
